{"id":"30349","coordinates":{"lat":"174.001","lng":"-41.2905926"},"media":{"alt":"New Zealand Trip Planner","src":"https://back.triptile.com/sites/default/files/2024-05/aneta-hartmannova-ph-lddjs6vc-unsplash_1.jpg"},"regions":"New Zealand","title":"New Zealand","content":"# Yeni Zelanda Rehberi: Doğal Güzellikler, Macera ve Kültürün Buluşma Noktası\n\nYeni Zelanda, nefes kesen manzaraları, macera dolu aktiviteleri ve zengin kültürel mirasıyla dünyanın dört bir yanından gezginleri cezbeden eşsiz bir destinasyondur. Pasifik Okyanusu'nun güneybatısında yer alan bu ada ülkesi, Marlborough'nun yemyeşil üzüm bağlarından Rotorua'nın jeotermal harikalarına, Milford Sound'un görkemli fiyortlarından Coromandel Yarımadası'nın el değmemiş plajlarına kadar keşfedilmeyi bekleyen sayısız güzellik sunar. Bu kapsamlı Yeni Zelanda rehberi, bu olağanüstü ülkeyi ziyaret etmek isteyenler için kapsamlı bilgiler, pratik ipuçları ve kaçırılmaması gereken deneyimler sunmaktadır.\n\n## Yeni Zelanda Hakkında Bilmeniz Gerekenler\n\n### Yeni Zelanda'nın Öne Çıkan Özellikleri\n\nYeni Zelanda, coğrafi çeşitliliği ve doğal güzellikleriyle ünlüdür. İki ana adadan (Kuzey Adası ve Güney Adası) oluşan ülke, dağlar, volkanlar, yağmur ormanları, buzul gölleri ve kilometrelerce uzanan sahil şeridiyle adeta bir doğa harikasıdır. Ülkenin en yüksek noktası olan Aoraki/Mount Cook, Güney Alpleri'nde yer alır ve dağcılık tutkunları için popüler bir destinasyondur. Yeni Zelanda, aynı zamanda eşsiz flora ve faunasıyla da dikkat çeker. Ülkeye özgü kivi kuşu, nesli tükenmekte olan bir sembol haline gelmiştir.\n\n### Tarihi ve Kültürel Zenginlikler\n\nYeni Zelanda'nın tarihi, Polinezya'dan gelen Maori halkının yaklaşık 700 yıl önce adaya yerleşmesiyle başlar. Maoriler, zengin bir kültüre, geleneklere ve sanata sahiptir. 17. yüzyılda Avrupalıların gelmesiyle Yeni Zelanda'nın tarihi değişmeye başlamış ve 19. yüzyılda İngiliz kolonisi haline gelmiştir. Günümüzde Yeni Zelanda, çok kültürlü bir toplum yapısına sahiptir. Maori kültürü, ülkenin kimliğinin önemli bir parçasıdır ve ziyaretçilere benzersiz bir deneyim sunar.\n\n### Ulaşım Bilgileri\n\nYeni Zelanda'ya ulaşım genellikle hava yoluyla sağlanır. Auckland Uluslararası Havaalanı, ülkenin en büyük ve en işlek havaalanıdır ve dünyanın birçok şehrinden direkt uçuşlar mevcuttur. Şehirler arası ulaşım için iç hat uçuşları, otobüsler ve trenler kullanılabilir. Araç kiralamak da popüler bir seçenektir, çünkü ülkenin doğal güzelliklerini keşfetmek için özgürlük sağlar. Yeni Zelanda'da araç kullanırken dikkat edilmesi gereken en önemli nokta, trafiğin soldan aktığıdır.\n\n### Ziyaret İçin En İyi Zaman\n\nYeni Zelanda'yı ziyaret etmek için en iyi zaman, genellikle yaz ayları olarak kabul edilen Aralık-Mart aylarıdır. Bu dönemde hava sıcaklıkları ılıman ve güneşli olup, açık hava aktiviteleri için idealdir. Ancak, Yeni Zelanda'da hava durumu oldukça değişkendir ve gün içinde farklı mevsimleri yaşamak mümkündür. Bu nedenle, seyahatiniz için her türlü hava koşuluna uygun kıyafetler hazırlamanız önemlidir.\n\n### Gezilecek Yerler\n\nYeni Zelanda'da gezilecek yerler saymakla bitmez. İşte mutlaka görülmesi gereken bazı yerler:\n\n*   **Milford Sound:** Güney Adası'nda yer alan bu muhteşem fiyort, yüksek kayalıklar, şelaleler ve yağmur ormanlarıyla çevrilidir. Tekne turları, kano gezileri ve yürüyüşler ile Milford Sound'un güzelliklerini keşfedebilirsiniz.\n\n*   **Rotorua:** Kuzey Adası'nda yer alan Rotorua, jeotermal aktiviteyle ünlüdür. Kaynayan çamur havuzları, gayzerler ve sıcak su kaynakları, Rotorua'yı benzersiz bir destinasyon haline getirir. Maori kültürünü deneyimlemek için de harika bir yerdir.\n\n*   **Queenstown:** Güney Adası'nda yer alan Queenstown, macera başkenti olarak bilinir. Bungy jumping, rafting, jet boting, kayak ve snowboard gibi birçok adrenalin dolu aktiviteyi burada deneyebilirsiniz. Ayrıca, muhteşem göl ve dağ manzaralarıyla da büyüler.\n\n*   **Auckland:** Yeni Zelanda'nın en büyük şehri olan Auckland, hareketli şehir hayatı, güzel plajları ve yemyeşil parklarıyla dikkat çeker. Sky Tower, Auckland Müzesi ve Waiheke Adası, Auckland'da görülmesi gereken yerler arasındadır.\n\n*   **Wellington:** Yeni Zelanda'nın başkenti olan Wellington, kültürel etkinlikleri, müzeleri, sanat galerileri ve canlı gece hayatıyla öne çıkar. Te Papa Müzesi, Wellington Botanik Bahçesi ve Zealandia Ecosanctuary, Wellington'da ziyaret edilebilecek yerlerdir.\n\n### Önerilen Aktiviteler\n\nYeni Zelanda'da yapılabilecek aktiviteler de oldukça çeşitlidir. İşte bazı öneriler:\n\n*   **Yürüyüş ve Trekking:** Yeni Zelanda, dünyanın en iyi yürüyüş parkurlarına ev sahipliği yapar. Tongariro Alpine Crossing, Abel Tasman Coast Track ve Routeburn Track gibi parkurlarda unutulmaz deneyimler yaşayabilirsiniz.\n\n*   **Su Sporları:** Yeni Zelanda'nın uzun sahil şeridi, su sporları için idealdir. Sörf, yelken, kano, dalış ve balık tutma gibi aktiviteleri deneyebilirsiniz.\n\n*   **Kayak ve Snowboard:** Güney Alpleri, kış sporları için mükemmel bir destinasyondur. Queenstown, Wanaka ve Methven gibi kayak merkezlerinde kayak ve snowboard yapabilirsiniz.\n\n*   **Maori Kültürünü Deneyimleme:** Maori kültürünü deneyimlemek için Rotorua'yı ziyaret edebilirsiniz. Geleneksel dans gösterilerini izleyebilir, Maori yemeklerini tadabilir ve Maori sanatını öğrenebilirsiniz.\n\n*   **Şarap Tadımı:** Yeni Zelanda, dünya çapında ünlü şaraplara ev sahipliği yapar. Marlborough, Central Otago ve Hawke's Bay gibi bölgelerde şarap tadımı turlarına katılabilirsiniz.\n\n### Yerel Lezzetler ve Gastronomi\n\nYeni Zelanda mutfağı, yerel malzemeler ve farklı kültürlerin etkisiyle zenginleşmiştir. İşte tadılması gereken bazı lezzetler:\n\n*   **Hangi Pie:** Etli turta, Yeni Zelanda'nın en popüler atıştırmalıklarından biridir. Farklı dolgularla hazırlanan hangi pie, her yerde bulunabilir.\n\n*   **Kumara:** Tatlı patates, Maori mutfağının önemli bir parçasıdır. Fırında pişirilmiş, kızartılmış veya püre haline getirilmiş olarak servis edilir.\n\n*   **Pavlova:** Beze tabanlı bir tatlı olan pavlova, genellikle meyveler ve krema ile süslenir. Yeni Zelanda'nın en sevilen tatlılarından biridir.\n\n*   **Hangi:** Geleneksel Maori yemeği olan hangi, toprak altında pişirilir. Et, sebze ve deniz ürünleri, sıcak taşlar üzerinde pişirilerek hazırlanır.\n\n*   **Whitebait Fritters:** Küçük balıkların yumurta ve unla karıştırılarak kızartılmasıyla yapılan whitebait fritters, yerel bir lezzettir.\n\n### Pratik Bilgiler ve İpuçları\n\n*   **Para Birimi:** Yeni Zelanda'nın para birimi Yeni Zelanda Doları'dır (NZD). Kredi kartları, özellikle Visa ve MasterCard, yaygın olarak kabul edilir.\n\n*   **Dil:** Yeni Zelanda'nın resmi dilleri İngilizce ve Maori'dir.\n\n*   **Vize:** Türkiye Cumhuriyeti vatandaşları, Yeni Zelanda'ya turistik amaçlı seyahatler için vize almak zorundadır.\n\n*   **Elektrik:** Yeni Zelanda'da elektrik voltajı 230V ve frekansı 50Hz'dir. Prizler, Avustralya ve Arjantin'de kullanılan tipte olup, adaptöre ihtiyaç duyabilirsiniz.\n\n*   **Su:** Yeni Zelanda'da musluk suyu genellikle güvenlidir, ancak bazı bölgelerde kaynatılması tavsiye edilir.\n\n*   **İklim:** Yeni Zelanda'da iklim ılıman deniz iklimidir. Yazları sıcak ve kurak, kışları ise ılıman ve yağışlıdır.\n\n*   **Acil Durumlar:** Acil durumlarda 111'i arayabilirsiniz (polis, itfaiye ve ambulans için).\n\n### Yeni Zelanda: Macera ve Doğanın Kalbinde Unutulmaz Bir Yolculuk\n\nYeni Zelanda, doğal güzellikleri, macera dolu aktiviteleri ve zengin kültürel mirasıyla her gezginin hayallerini süsleyen bir destinasyondur. İster Milford Sound'un görkemli fiyortlarında tekne turuna katılın, ister Queenstown'da adrenalin dolu aktivitelere atılın, ister Rotorua'da Maori kültürünü deneyimleyin, Yeni Zelanda size unutulmaz bir deneyim vadediyor. Bu kapsamlı rehber, Yeni Zelanda seyahatinizi planlamanıza ve bu olağanüstü ülkenin sunduğu tüm güzellikleri keşfetmenize yardımcı olacaktır. Hazırlıklarınızı yapın ve Yeni Zelanda'nın büyüleyici dünyasına adım atın!\n"}