{"title":"Ashland Oregon Gezi Rehberi: En İyi 10 Aktivite ile Keşfet!","featuredImage":{"src":"https://lp-cms-production.imgix.net/2024-05/Tamara-Gane.jpg?auto=format,compress&q=72&crop=faces&fit=crop&w=64&h=64","alt":"Tamara Gane","caption":"From rafting the Rogue River to seeing theatrical performances, here are the\nbest things to do in and around Ashland, Oregon © Erik Isakson / Getty Images"},"output":{"title":"Ashland, Oregon ve Çevresinde Yapılabilecek En İyi 10 Şey","content":"Ashland, Oregon sadece Shakespeare festivalinden ibaret değil! Şehrin sunduğu kültürel zenginlikler ve doğal güzellikler keşfedilmeyi bekliyor. Güney Oregon'un incisi Ashland ve çevresinde yapabileceğiniz en iyi 10 aktiviteyi keşfetmeye hazır mısınız? Bu rehber, **Ashland, Oregon ve Çevresinde Yapılabilecek Aktiviteler** konusunda size rehberlik edecek ve unutulmaz bir seyahat deneyimi yaşamanızı sağlayacak.\n\nMeta Açıklama: Ashland, Oregon'da nereleri gezmeli, neler yapmalı? Kültürel etkinliklerden doğa sporlarına, lezzetli yemeklerden şarap tadımlarına en iyi 10 aktivite!\n\n## 1. Oregon Shakespeare Festivali ile Tiyatroya Doyun\n\nAshland denince akla ilk gelenlerden biri, şüphesiz Oregon Shakespeare Festivali. 1935'ten beri süregelen bu gelenek, her yıl Mart ayından Ekim ayına kadar üç farklı tiyatro sahnesinde klasik ve çağdaş oyunları tiyatroseverlerle buluşturuyor. Festival sadece Shakespeare eserleriyle sınırlı değil; geniş bir yelpazede farklı türlerdeki oyunlar da sahneleniyor. Eğer tiyatroya tutkunuz varsa, **Ashland, Oregon** seyahatinizi festival takvimine göre planlamanız şiddetle tavsiye edilir. Unutmayın, festival kapsamında Mayıs sonundan Ekim ortasına kadar haftanın dört günü (Çarşamba-Cumartesi) ücretsiz açık hava gösterileri de düzenleniyor. Bu gösteriler, hem yerel halk hem de turistler için keyifli bir etkinlik alternatifi sunuyor.\n\n### Neden Oregon Shakespeare Festivali'ni Ziyaret Etmelisiniz?\n\n*   **Zengin Repertuvar:** Klasiklerden modern uyarlamalara kadar geniş bir oyun seçkisi.\n*   **Usta Oyuncular:** Alanında yetenekli ve deneyimli oyuncu kadrosu.\n*   **Büyülü Atmosfer:** Tiyatroların tarihi dokusu ve festivalin coşkusu.\n*   **Ücretsiz Gösteriler:** Herkese açık ve ücretsiz açık hava performansları.\n\n## 2. Oregon Cabaret Theater'da Unutulmaz Bir Akşam Geçirin\n\nTiyatro keyfinize yemek ve eğlenceyi de katmak isterseniz, Oregon Cabaret Theater tam size göre. Yıl boyunca açık olan bu akşam yemeği tiyatrosu, hem lezzetli yemekler sunuyor hem de çeşitli müzikal ve komedi oyunlarına ev sahipliği yapıyor. **Ashland, Oregon**'da farklı bir akşam geçirmek isteyenler için ideal bir seçenek.\n\n## 3. Ashland New Plays Festival ile Yeni Yetenekleri Keşfedin\n\nSahne sanatlarına meraklıysanız ve yeni yetenekleri keşfetmekten hoşlanıyorsanız, Ashland New Plays Festivali'ni kaçırmayın. Bu festival, yeni oyun yazarlarını desteklemeyi amaçlıyor ve onların eserlerinin sahnelenmesine olanak tanıyor. Belki de geleceğin yıldızlarını ilk siz keşfedeceksiniz!\n\n## 4. Sanat Galerilerinde Ruhunuzu Besleyin\n\n**Ashland, Oregon**, sadece tiyatroyla değil, aynı zamanda sanatla da iç içe bir şehir. Şehirde 30'dan fazla sanat galerisi ve stüdyo bulunuyor. Her ayın ilk Cuma günü düzenlenen First Friday Artwalk etkinliği ile bu galerileri ziyaret edebilir, yerel sanatçıların eserlerini yakından görebilir ve hatta satın alabilirsiniz. Sanatla iç içe bir gün geçirmek için harika bir fırsat.\n\n### First Friday Artwalk Nedir?\n\nHer ayın ilk Cuma günü, Ashland'daki sanat galerileri kapılarını saat 17:00-20:00 arasında ücretsiz olarak ziyaretçilere açar. Bu etkinlik, yerel sanatçıları desteklemek ve sanatseverleri bir araya getirmek amacıyla düzenlenir.\n\n## 5. Lithia Artisans Market'te El Yapımı Ürünlere Göz Atın\n\nMart ayından Ekim ayına kadar hafta sonları kurulan Lithia Artisans Market, yerel zanaatkarların el yapımı ürünlerini sergilediği ve sattığı bir pazar. Burada takılardan seramiklere, ahşap oymalarından tekstil ürünlerine kadar birçok farklı el yapımı ürün bulabilirsiniz. Sevdiklerinize **Ashland, Oregon**'dan otantik bir hediye almak isterseniz, burası tam size göre.\n\n## 6. Schneider Museum of Art'ta Sanatın Derinliklerine Dalın\n\nSouthern Oregon Üniversitesi kampüsünde bulunan Schneider Museum of Art, düzenli olarak görsel sanatlar sergileri düzenliyor. Müzede, modern ve çağdaş sanat eserlerinin yanı sıra, farklı dönemlere ait koleksiyonlar da sergileniyor. Sanatseverler için kaçırılmaması gereken bir durak.\n\n## 7. Oregon Center for the Arts'ta Canlı Performansların Keyfini Çıkarın\n\nSouthern Oregon Üniversitesi bünyesinde faaliyet gösteren Oregon Center for the Arts, canlı müzik ve tiyatro etkinliklerine ev sahipliği yapıyor. Konserlerden tiyatro oyunlarına, dans gösterilerinden film gösterimlerine kadar çeşitli etkinliklerle **Ashland, Oregon**'ın kültürel hayatına renk katıyor.\n\n## 8. Rogue ve Klamath Nehirlerinde Rafting ve Kano ile Coşun\n\nDoğa sporlarına meraklıysanız, **Ashland, Oregon** tam size göre. Rogue ve Klamath nehirlerinin coğrafi yakınlığı, rafting ve kano gibi su sporları için ideal bir ortam sunuyor. Bölgede, farklı zorluk seviyelerine sahip rafting turları düzenleyen birçok işletme bulunuyor. Unutulmaz bir macera için kollarınızı sıvayın!\n\n### Rafting ve Kano İçin İpuçları\n\n*   **Sezonu Kontrol Edin:** Rafting ve kano için en uygun zaman genellikle ilkbahar ve yaz aylarıdır.\n*   **Uygun Ekipmanları Seçin:** Güvenliğiniz için kask, can yeleği gibi ekipmanları eksiksiz kullanın.\n*   **Tecrübeli Bir Rehberle Çalışın:** Özellikle ilk kez rafting veya kano yapıyorsanız, tecrübeli bir rehberle çalışmanız önemlidir.\n\n## 9. Lithia Park'ta Doğayla İç İçe Olun\n\nŞehir merkezinde bulunan Lithia Park, 40 hektarlık devasa bir alana yayılıyor. Park içerisinde çim alanlar, tenis/pickleball sahaları, voleybol sahası, çocuk oyun alanı, piknik alanları, kış aylarında buz pateni pisti ve yürüyüş parkurları bulunuyor. Şehrin gürültüsünden uzaklaşmak ve doğayla iç içe vakit geçirmek için ideal bir mekan.\n\n### Lithia Park'ta Neler Yapabilirsiniz?\n\n*   **Yürüyüş:** Park içerisinde farklı zorluk seviyelerine sahip yürüyüş parkurları bulunuyor.\n*   **Piknik:** Aileniz veya arkadaşlarınızla birlikte keyifli bir piknik yapabilirsiniz.\n*   **Spor:** Tenis, pickleball veya voleybol oynayabilirsiniz.\n*   **Dinlenme:** Çimlerde uzanıp güneşin tadını çıkarabilir veya kitap okuyabilirsiniz.\n\n## 10. Çevre Bölgedeki Doğal Güzellikleri Keşfedin\n\n**Ashland, Oregon** sadece kendi sınırları içinde değil, çevresiyle de büyüleyici bir bölge. Yakınlardaki Cascade-Siskiyou National Monument, Rogue River-Siskiyou National Forest, Crater Lake ve Applegate Lake gibi doğal güzellikleri keşfederek seyahatinizi unutulmaz kılabilirsiniz.\n\n### Keşfedilmeyi Bekleyen Doğal Güzellikler\n\n*   **Grizzly Peak Trailhead:** Ashland şehir merkezine yaklaşık 19 kilometre uzaklıkta bulunan bu parkur, muhteşem manzaralar sunuyor.\n*   **Cascade-Siskiyou National Monument ve Rogue River-Siskiyou National Forest:** Yürüyüş, kamp ve diğer doğa sporları için ideal alanlar.\n*   **Crater Lake:** Volkanik bir krater gölü olan Crater Lake, dünyanın en derin göllerinden biri.\n*   **Applegate Lake:** Tekne gezintisi, balık tutma ve su sporları için mükemmel bir seçenek.\n\n## Ashland'ın Lezzetlerini Tadın\n\n**Ashland, Oregon**, sadece doğal güzellikleri ve kültürel etkinlikleriyle değil, aynı zamanda lezzetli yemekleriyle de öne çıkıyor. Şehirde farklı bütçelere ve zevklere uygun birçok restoran seçeneği bulunuyor.\n\n*   **Lark’s Home Kitchen Cuisine:** Yerel çiftlik ürünleriyle hazırlanan menüsüyle dikkat çekiyor.\n*   **Harvey’s Place:** Hamburgerlerden salatalara ve et yemeklerine kadar geniş bir yelpazede seçenek sunuyor.\n*   **Sammich:** Chicago tarzı sandviçleriyle ünlü.\n\n## Ashland'da Şarap, Bira ve Kahve Keyfi\n\n**Ashland, Oregon**, aynı zamanda şarap, bira ve kahve tutkunları için de cennet gibi bir yer. Bölgede birçok şarap tadım odası, bira fabrikası ve kahve dükkanı bulunuyor.\n\n*   **Rogue Valley AVA:** Bölgede üretilen şarapları tadabilirsiniz.\n*   **Caldera Brewery and Restaurant:** Yerel şerbetçiotlarıyla üretilen biraları deneyebilirsiniz.\n*   **Rogue Valley Roasting Co ve Case Coffee Roasters:** Taze kavrulmuş kahveleri yudumlayabilirsiniz.\n\n## Ashland'da Nerede Kalınır?\n\n**Ashland, Oregon**'da konaklama için birçok farklı seçenek bulunuyor. Şehir merkezinde veya çevresinde otel, motel, pansiyon veya kiralık ev gibi birçok alternatif bulabilirsiniz.\n\n*   **Ashland Hills Hotel and Suites:** Şehir merkezinin dışında, yüksek bir konumda yer alıyor.\n*   **Ashland Springs Hotel:** Şehir merkezinde bulunan tarihi bir otel.\n\n## Sonuç: Ashland, Oregon Sizi Bekliyor!\n\n**Ashland, Oregon ve Çevresinde Yapılabilecek Aktiviteler** saymakla bitmiyor. İster kültür ve sanatla dolu bir tatil, ister doğayla iç içe bir macera arayın, Ashland size unutulmaz bir deneyim sunacak. Tarihi tiyatroları, canlı sanat ortamı, nefes kesen doğal güzellikleri ve lezzetli mutfağıyla Ashland, keşfedilmeyi bekleyen bir cennet. Bu rehberde bahsettiğimiz 10 aktivite sadece başlangıç. Gelin, bu güzel şehri keşfedin ve kendi unutulmaz anılarınızı yaratın!\n\n**Şimdi sıra sizde!** **Ashland, Oregon**'ı ziyaret etmeyi düşünüyor musunuz? Hangi aktiviteler sizi daha çok heyecanlandırıyor? Yorumlarda bizimle paylaşın ve seyahat planlarınızı birlikte yapalım! Unutmayın, en güzel anılar, keşfedilmeyi bekleyen yerlerde saklıdır."},"media":[{"src":"https://lp-cms-production.imgix.net/2024-09/Oregon-Shakespeare-Festival.jpg??auto=format,compress&amp;q=72&amp;w=920&amp;h=950&amp;dpr=2","alt":"Performers onstage in an open-air theater against a pink sunset.","figcaption":" The Oregon Shakespeare Festival program runs from May to October © Kim Budd / Oregon Shakespeare Festival "},{"src":"https://lp-cms-production.imgix.net/2024-04/shutterstock2035761404-1.jpg??auto=format,compress&amp;q=72&amp;w=920&amp;h=950&amp;dpr=2","alt":"A park sign welcomes visitors to Lithia Park","figcaption":" Lithia Park is Ashland's beautiful landscaped city park with fountains, flowers and gazebos ©&nbsp;Lynn Watson / Shutterstock "},{"src":"https://lp-cms-production.imgix.net/2024-04/GettyImages-1253182073.jpg??auto=format,compress&amp;q=72&amp;w=920&amp;h=950&amp;dpr=2","alt":"A small boat sails along a huge pine-lined lake","figcaption":" Applegate Lake is about an hour's drive from Ashland © Strekoza2 / Getty Images "},{"src":"https://lp-cms-production.imgix.net/2024-09/downtown-ashland-oregon.jpg??auto=format,compress&amp;q=72&amp;w=920&amp;h=950&amp;dpr=2","alt":"Ppretty brick storefronts of a small town under a blue night's sky","figcaption":" Admire the restored historic shopfronts of downtown Ashland © Mona Makela Photography / Lonely Planet "}],"id":1743419330486,"cities":["Ashland"],"countries":["Oregon"],"description":"Ashland, Oregon'da gezilecek yerler ve yapılacak aktiviteler mi arıyorsunuz? Tiyatrodan doğa sporlarına, en iyi 10 deneyimi keşfedin. Ashland gezi rehberi burada!","excerpt":"Ashland, Oregon, Shakespeare festivali ve doğal güzellikleriyle ünlü. Bu gezi rehberi ile Ashland ve çevresinde tiyatro, sanat, doğa sporları ve lezzet duraklarını keşfedin. Unutulmaz bir seyahat deneyimi için en iyi 10 aktivite!","keywords":["Ashland Oregon","Ashland Gezi Rehberi","Oregon Shakespeare Festivali","Lithia Park","Rogue Nehri","Ashland Aktiviteler","Güney Oregon"]}