{"title":"Cartagena Gezi Rehberi: En İyi 12 Deneyimle Karayip Rüyası","featuredImage":{"src":"https://lp-cms-production.imgix.net/2022-10/laura.blake%20-%20Laura%20Blake.jpg?auto=format,compress&q=72&crop=faces&fit=crop&w=64&h=64","alt":"Laura Watilo Blake","caption":"Discover top attractions, beaches, restaurants and street art in Cartagena,\nColombia’s historic walled city. Atosan/Shutterstock"},"output":"{\n  \"title\": \"Cartagena'da Yapılacak En İyi 12 Şey: Karayip Coşkusunu Keşfedin\",\n  \"content\": \"## Cartagena'da Yapılacak En İyi 12 Şey: Karayip Coşkusunu Keşfedin\\n\\nKarayip'in incisi Cartagena, Kolombiya, renkli tarihi, canlı kültürü ve nefes kesen doğal güzellikleriyle ziyaretçilerini büyüleyen bir şehir. İster tarih meraklısı olun, ister macera arayan bir gezgin, ister sadece dinlenmek isteyen bir tatilci, Cartagena'da herkes için bir şeyler var. İşte Cartagena'da mutlaka yapmanız gereken 12 şey:\\n\\n### 1. Cartagena'nın Surlarla Çevrili Şehrinin Labirent Sokaklarında Kaybolun\\n\\nCartagena'nın kalbi, UNESCO Dünya Mirası Listesi'nde yer alan surlarla çevrili eski şehirdir. 17. yüzyılda korsan saldırılarına karşı koruma sağlamış bu kalın mercan duvarlar arasında yürürken, tarih adeta canlanıyor. Rengarenk kolonyal mimarisi, hareketli meydanları ve dar sokaklarıyla bu büyüleyici labirentte kaybolmak, unutulmaz bir deneyim sunuyor.\\n\\n*   **Plaza de Bolívar:** İspanyol sömürge döneminin izlerini taşıyan bu meydanda, Palacio de la Inquisición'u (Engizisyon Sarayı) ve Santuario de San Pedro Claver'i ziyaret edebilirsiniz.\\n*   **Ábaco Libros y Café:** Sıcak tropikal güneşten kaçmak ve kitaplarla dolu bir ortamda kahve keyfi yapmak için ideal bir yer.\\n\\n### 2. Castillo San Felipe de Barajas'ın Mühendislik Harikasına Hayran Kalın\\n\\nCartagena'nın en ikonik simgelerinden biri olan Castillo San Felipe de Barajas, Güney Amerika'nın en büyük kalesi olma özelliğini taşıyor. Şehre ve denize hakim bir tepede yer alan bu etkileyici yapı, 16. yüzyılda inşa edilmiş ve zaman içinde birçok kez genişletilmiş. Kalenin içindeki dar tünellerde dolaşmak, savunma stratejilerini anlamak için harika bir yol. Gün batımını izlemek için kalenin en yüksek noktasına çıkmayı unutmayın.\\n\\n### 3. Bohem Getsemaní'nin Sanatını Deneyimleyin\\n\\nEskiden işçi sınıfının yaşadığı bir mahalle olan Getsemaní, günümüzde sanat dolu bir bölgeye dönüştü. Duvar resimleriyle süslü dar sokakları, canlı meydanları ve hareketli gece hayatıyla Getsemaní, Cartagena'nın en renkli köşelerinden biri. Plaza de la Trinidad'da oturup yerel lezzetleri tadabilir, sokak sanatçılarını izleyebilir ve gece geç saatlere kadar eğlenebilirsiniz.\\n\\n### 4. Cartagena'nın Plajlarında Gevşeyin\\n\\nCartagena'nın plajları, Kolombiya'nın diğer kıyı bölgelerindeki kadar muhteşem olmasa da, kolay erişilebilir olmaları ve sundukları olanaklar sayesinde popüler bir seçenek. Bocagrande plajı, Miami Beach'e benzetilen uzun bir sahil şeridi. Daha sakin bir ortam arıyorsanız, Castillogrande'deki Playa El Laguito'yu tercih edebilirsiniz. Buradan tekne kiralayarak Tierra Bomba adasına veya Rosario Adaları'na gidebilirsiniz.\\n\\n### 5. Gün Batımında Bir Çatı Katı Vahasında Kokteyllerinizi Yudumlayın\\n\\nCartagena'nın kıyı konumu, güneşin denizin üzerinde batışını izlemek için mükemmel bir fırsat sunuyor. Şehirdeki birçok çatı barı, bu anı unutulmaz kılmak için harika bir seçenek. Café del Mar, şehir surlarının üzerinde yer alan ikonik bir mekan. Townhouse Rooftop, Mirador Gastrobar ve 51 Sky Bar da popüler seçenekler arasında.\\n\\n### 6. Bir Salsa Kulübünde Dans Pisti Etrafında Dönün\\n\\nSalsa, Küba'dan çıkmış olsa da, Kolombiyalılar bu müzik türünü benimsemiş ve kendilerine özgü bir tarz geliştirmişler. Cartagena'daki salsa kulüpleri, ister deneyimli bir dansçı olun, ister ilk adımlarınızı atıyor olun, herkesi dans etmeye teşvik eden sıcak bir atmosfere sahip. Café Havana ve Club Los Carpinteros, popüler salsa kulüplerinden bazıları.\\n\\n### 7. Cartagena'nın Restoranlarının, Sokak Lezzetlerinin ve Pazar Yemeklerinin Tadını Çıkarın\\n\\nCartagena, yerel lezzetleri dünya mutfaklarıyla harmanlayan çeşitli restoranlara sahip. Mar y Zielo, Celele ve La Vitrola, popüler restoranlardan bazıları. Sokaklarda dolaşırken, patacones (kızarmış muz), papas rellenas (kıymalı patates topları) ve arepa de huevo (yumurtalı arepa) gibi yerel lezzetleri tadabilirsiniz. Mercado Bazurto, egzotik tropikal meyveleri ve yöresel yemekleri keşfetmek için harika bir yer.\\n\\n### 8. Bir Chiva Parti Otobüsüyle Cartagena Sokaklarında Gezin\\n\\nGüneş battıktan sonra, Cartagena'nın gece hayatı, chiva parti otobüsleri ile canlanıyor. Chivalar, kırsal bölgelerde kullanılan geleneksel bir ulaşım aracıdır. Cartagena'da bu renkli otobüsler, müzik, dans ve içki eşliğinde şehrin sokaklarında gezintiye çıkmak için kullanılıyor.\\n\\n### 9. Museo del Oro Zenú'da Altına Hücum Edin\\n\\nMuseo del Oro Zenú, Kolombiya Karayip bölgesindeki 6000 yıllık pre-İspanyol kültürünü temsil eden eserleri sergiliyor. Müzedeki en önemli bölüm, altın ve tumbaga (altın ve bakır alaşımı) ile yapılmış benzersiz eserlerin sergilendiği kalıcı koleksiyon. Zenú zanaatkarları, doğal ve ruhani dünyayı temsil eden benzersiz sanat eserleri yaratmak için döküm, çekiçleme, gravür ve kakma tekniklerini kullanmışlar.\\n\\n### 10. Convento de la Popa'dan Manzaraya Tapın\\n\\nConvento de la Popa, Cartagena'nın en yüksek tepesinde yer alıyor ve şehre hakim bir konumda bulunuyor. Manastırın içindeki avlu, tropikal bitkilerle dolu. Buradan Cartagena'nın 360 derecelik panoramik manzarasını izleyebilirsiniz.\\n\\n### 11. Kolombiya Kahvesiyle Kendinize Gelin\\n\\nKolombiya'yı ziyaret etmek, dünyaca ünlü kahvesini tatmadan tamamlanmış sayılmaz. Cartagena'da birçok kahve dükkanı, ülkenin en iyi kahvelerini sunuyor. Café San Alberto, Época Espresso Bar ve Libertario Coffee Roasters, popüler kahve dükkanlarından bazıları.\\n\\n### 12. La Boquilla'ya Sınır Oluşturan Kıyı Mangrovlarında Balık Tutmaya Gidin\\n\\nEcotours Boquilla ile Karayip kıyısındaki mangrovlarda kano gezisi yapmak, sadece güzel bir tekne gezisinden daha fazlası. Bu gezi, La Boquilla kıyı köyünün kültürel mirasını korumak için önemli bir yol. Yerel balıkçılar, balık ağları ve yengeç tuzakları hakkında bilgi aktararak tur rehberi rolünü üstleniyorlar.\\n\\n**Meta Açıklama:** Cartagena'da yapılacak en iyi 12 şeyle Karayip coşkusunu keşfedin! Tarihi sokaklarda kaybolun, muhteşem manzaralara tanık olun, yerel lezzetleri tadın ve unutulmaz anılar biriktirin.\n\"\n}","media":[{"src":"https://lp-cms-production.imgix.net/2024-11/Shutterstock510842902.jpg?auto=format,compress&amp;q=72&amp;fit=crop","alt":"Cartagena, Colombia. Church of St Peter Claver.","figcaption":"Located inside the Old Town, the Church of St Peter Claver was built built in the 16th century. Shutterstock"},{"src":"https://lp-cms-production.imgix.net/2023-08/GettyImages-85643708.jpg?auto=format,compress&amp;q=72&amp;fit=crop","alt":"A woman and a man standing at a fruit vendor's cart in colorful Cartagena","figcaption":"Pick up a light snack at one of Cartagena's many street food stalls. Jupiterimages/Getty Images"},{"src":"https://lp-cms-production.imgix.net/2024-11/shutterstock2080859326.jpg?auto=format,compress&amp;q=72&amp;fit=crop","alt":"The dancers and musicians present the musical number of colombian caribbean to the tourists in the Cafe del Mar, on the wall of Cartagena at the sunset.","figcaption":"Join the revelery while taking in the sunset at Café del Mar. WILLIAM RG/Shutterstock"},{"src":"https://lp-cms-production.imgix.net/2023-08/shutterstockRF1210420141.jpg?auto=format,compress&amp;q=72&amp;fit=crop","alt":"Woman selling fried street food at a stall in Cartagena","figcaption":"Take to the streets to find some deeply delicious fried Colombian dishes. Anamaria Mejia/Shutterstock"},{"src":"https://lp-cms-production.imgix.net/2023-08/500pxRF114128673.jpg?auto=format,compress&amp;q=72&amp;fit=crop","alt":"A view of Cartagena from the Convento de la Popa","figcaption":"The views from Convento de la Popa are definitely worth the pilgrimage. Jess Kraft/500px"}],"id":1743130777958,"cities":["Cartagena"],"description":"Cartagena'da yapılacak en iyi 12 şeyle Karayip coşkusunu yaşayın! Tarihi sokakları, plajları ve lezzetleriyle unutulmaz bir Cartagena deneyimi sizi bekliyor.","excerpt":"Cartagena, Kolombiya'nın incisi, tarihi, kültürü ve doğal güzellikleriyle büyüleyici bir şehir. Surlarla çevrili sokaklarda kaybolun, kaleleri keşfedin, Getsemaní'nin sanatını deneyimleyin, plajlarda dinlenin ve Karayip lezzetlerini tadın. Cartagena'da yapılacak en iyi 12 şey ile unutulmaz bir deneyim yaşayın.","keywords":["Cartagena gezilecek yerler","Cartagena'da yapılacaklar","Cartagena gezi rehberi","Cartagena Karayip","Cartagena Kolombiya","Karayip tatili","Kolombiya seyahati"]}