{"title":"Fransa Seyahat Rotaları: En İyi 5 Güzergah ile Fransa'yı Keşfet!","featuredImage":{"src":"https://lp-cms-production.imgix.net/2022-03/Nicola.Williams%20-%20Nicola%20Williams.jpg?auto=format,compress&q=72&crop=faces&fit=crop&w=64&h=64","alt":"Nicola Williams","caption":"The promenade in the center of Menton, on the French Riviera. Andrei\nAntipov/Shutterstock"},"output":{"title":"Fransa Seyahat Rotaları: Ülkenin En İyilerini Görmek İçin 5 Farklı Güzergah","content":"Fransa, her köşesinde ayrı bir güzellik barındıran, zengin tarihi, kültürel mirası ve doğal çeşitliliği ile gezginlerin hayallerini süsleyen bir ülke. İster Normandiya kıyılarında taze istiridyelerin tadına bakın, ister Bordeaux'da dünyaca ünlü şarapları yudumlayın, isterseniz de Paris'in büyüleyici sokaklarında kaybolun; Fransa'da unutulmaz bir tatil deneyimi sizi bekliyor. Bu blog yazısında, Fransa'nın en ikonik yerlerini keşfetmek, Atlantik kıyısında keyifli bir yolculuk yapmak, Güney Fransa'nın güneşli atmosferini solumak, Breton istiridyeleri ve Norman peynirlerinin tadına varmak veya Eurostar ile Calais'den Alpler'e uzanan bir maceraya atılmak için 5 farklı seyahat rotasını inceleyeceğiz.\n\n## Fransa'yı Keşfetmek İçin 5 Muhteşem Rota\n\nFransa'yı keşfetmek için sayısız yol var. İster kısa bir hafta sonu kaçamağı, ister uzun ve detaylı bir tatil planlayın, bu rehber size ilham verecek ve seyahatinizi planlamanıza yardımcı olacak.\n\n### 1. Fransa'nın En İkonik Yerleri: 9 Günlük Bir Rota\n\nEğer Fransa'nın en meşhur yerlerini görmek gibi bir hayaliniz varsa, bu 9 günlük rota tam size göre. Dünyaca ünlü müzeler, görkemli şatolar, Roma kalıntıları ve hareketli sahil şehirleri sizi bekliyor. Vaktiniz varsa, her bir durakta birkaç gün daha kalarak deneyiminizi zenginleştirebilirsiniz.\n\n*   **Paris (2 gün):** Eyfel Kulesi'nden şehrin panoramik manzarasını seyredin, Arc de Triomphe'un tepesinden Paris'i kuşbakışı görün, Sainte-Chapelle'in büyüleyici atmosferinde bir konser dinleyin ve Versailles Sarayı'nın ihtişamına tanık olun. Kafe kültürünün tadını çıkarın, bistrolarda öğle yemeği yiyin ve Seine Nehri kıyısında romantik bir yürüyüş yapın.\n\n*   **Blois (1 gün):** Blois, bir zamanlar güçlü kontların feodal merkezi olan küçük bir kasaba. Tarihi dokusu, Rönesans mimarisi ve etkileyici şatosu ile ziyaretçilerini cezbediyor. Bisiklet kiralayarak Château de Chambord'u keşfedebilirsiniz.\n\n*   **Vézère Vadisi (1 gün):** Dordogne bölgesindeki bu kırsal vadi, tarih öncesi sanatçıların çizimleriyle süslenmiş mağaralarıyla ünlü. Musée National de Préhistoire'ı ziyaret ederek bölgenin tarihini öğrenin ve Grotte de Font de Gaume ve Lascaux mağaralarına girerek büyüleyici bir deneyim yaşayın.\n\n*   **Carcassonne (1 gün):** Güneydeki Lot'un Causses de Quercy bölgesinin vahşi doğasından sonra, Carcassonne'un kalabalığı sizi şaşırtabilir. Ancak, kasulet yemeği eşliğinde keyifli bir öğle yemeği molası verin ve gün batımında masalsı kaleyi ziyaret edin.\n\n*   **Pont du Gard (1 gün):** Roma tarihine meraklıysanız, burası tam size göre. UNESCO Dünya Mirası Listesi'nde yer alan bu etkileyici Roma su kemeri, mühendislik harikası olarak kabul ediliyor. Yüzme kıyafetlerinizi yanınıza alarak, anıtı keşfettikten sonra yakındaki kayalıklardan atlayışlar yapabilirsiniz.\n\n*   **Arles (1 gün):** Camargue'ın başkenti Arles, güneyin çekici bir şehri. Van Gogh'a ilham veren altın renkli sokaklarda yürüyün, Roma amfitiyatrosunda geçmişe yolculuk yapın ve cumartesi sabahı pazarında yöresel ürünler satın alın. Frank Gehry tarafından tasarlanan Fondation Luma'yı ziyaret ederek çağdaş sanatın tadını çıkarın.\n\n*   **Marsilya (2 gün):** Provence'ın hareketli metropolü Marsilya'nın enerjisine kendinizi bırakın. Vieux Port'taki balıkçılarla sohbet edin, sahil boyunca uzanan plajlarda güneşlenin ve Les Calanques'ta yürüyüş yapın veya kano ile gezintiye çıkın.\n\n### 2. Atlantik Kıyısında Keyifli Bir Yolculuk: 7 Günlük Bir Rota\n\nDeniz melteminin teninizi okşadığı, uçsuz bucaksız üzüm bağlarının ve Avrupa'nın en büyük kum tepesinin sizi büyüleyeceği bir yolculuğa hazır olun. Fransa'nın Atlantik kıyısı, her köşesinde kartpostallık manzaralar ve lezzetli yemeklerle dolu bir cennet. Köyler ve bağlar arasında özgürce dolaşmak için araba kiralamak ideal olsa da, trenle seyahat etmek daha çevre dostu bir seçenek.\n\n*   **Nantes (1 gün):** Atlantik Okyanusu ve Loire Nehri'nin kesişim noktasında yer alan Nantes, Bretonya'nın eski başkenti. Les Machines de l’Île'de mekanik hayvanları görün, şehrin şatosunu ziyaret edin ve Le Voyage à Nantes sanat rotasını takip ederek şehrin sokaklarında dolaşın. Hangar à Bananes'ta gün batımını izleyerek keyifli bir akşam geçirin.\n\n*   **La Rochelle (2 gün):** 14. yüzyıldan 17. yüzyıla kadar önemli bir Fransız limanı olan La Rochelle, günümüzde de Fransa'nın en çekici denizcilik şehirlerinden biri. Şehrin denizcilik kulelerine tırmanarak kuşbakışı manzaranın tadını çıkarın, muhteşem deniz ürünlerinin tadına bakın ve Île de Ré adasında bisiklet turu yapın.\n\n*   **Bordeaux (1 gün):** Mimari harikaları, sanat eserleri, lezzetli yemekleri ve dünyaca ünlü şaraplarıyla Bordeaux'da geçireceğiniz bir gün, hayatınızın en güzel günlerinden biri olabilir. Şehrin tarihi kısmı UNESCO Dünya Mirası Listesi'nde yer alıyor. Ancak, Bordeaux'nun çağdaş müzeleri ve sanat galerileri de görülmeye değer.\n\n*   **Arcachon (2 gün):** Palmiye ve çam ağaçlarıyla çevrili Arcachon'da eski moda deniz kenarı cazibesinin tadını çıkarın. Altın kumlu plajda güneşlenin, deniz manzaralı restoranlarda deniz ürünleri yiyin ve tekneyle Cap Ferret ve Île aux Oiseaux'a gidin. Dune du Pilat'a bisikletle gitmek, kum tepesinin kendisi kadar heyecan verici.\n\n*   **Bayonne (1 gün):** Kaliteli çikolatası, jambonu ve Bask kültürüyle ünlü Bayonne, vaktinizi ayırmaya değer. Gökkuşağı renklerindeki ahşap evlerin arasında dolaşın ve Musée Basque et de l’Histoire de Bayonne'da Bask kültürünü yakından tanıyın. Ardından, Fransa'nın en iyi sıcak çikolatasının tadına bakın ve hareketli pazarda alışveriş yapın.\n\n### 3. Güney Fransa'nın Güneşli Atmosferini Keşfedin: 7 Günlük Bir Rota\n\nÜstü açık arabanızla keyifli bir sürüş yapmak için en uygun bölge olan Riviera'nın göz kamaştırıcı manzaralarına hazır olun. Temmuz ve Ağustos aylarında kalabalıktan kaçınarak bu rotayı takip edebilirsiniz. Bu rota sizi Côte d’Azur'un cazibesinden, Kuzey Provence'ın vahşi ve bakir vadilerine götürecek.\n\n*   **Nice (2 gün):** Olağanüstü modern sanat müzeleri, sokak pazarları, ikonik Akdeniz plajları ve labirent gibi sokaklarıyla Nice, Riviera'nın kraliçesi. Şehrin şefleri geleneksel yemekleri yarı gastronomik bir seviyeye yükseltiyor. Bu nedenle, günde üç öğün yemek yemeyi unutmayın.\n\n*   **Menton (1 gün):** İtalya'dan önceki son Fransız şehri olan Menton, limonları ve yıldız şef Mauro Colagreco sayesinde yeniden popülerleşti. La Ferme des Citrons'da limon çiftliğinde rehberli bir tura katılın ve teraslı bahçelerde öğle yemeği yiyin. Ardından, Eski Şehir'de dolaşarak bahçelerindeki mikro iklimi hayranlıkla izleyin.\n\n*   **St-Tropez (1 gün):** Sahil boyunca uzanan Corniche de l’Estérel yolu, Riviera'da araba kullanmanın en güzel örneklerinden biri. Efsanevi balıkçı köyü St-Tropez, aynı zamanda göz kamaştırıcı bir turistik merkez.\n\n*   **Bormes-les-Mimosas (4 saat):** Bormes-les-Mimosas'a giden her yol, nefes kesen manzaralar sunuyor. Ormanlık Massif des Maures'e dalın, Domaine du Rayol'daki deniz bahçelerini ziyaret edin ve Route des Crêtes'te keyifli bir sürüş yapın. Öğle yemeği molası verin ve ortaçağ köyündeki çiçek gösterilerini izleyin.\n\n*   **Aix-en-Provence (1 gün):** Görkemli mimarisi, çınar ağaçlarıyla gölgelenen zarif caddeleri, güneşin ısıttığı sokaklara yayılan kafeleri ve heykeltıraş taş çeşmeleriyle Aix-en-Provence, klasik Provence havasını yansıtıyor. Şehirde doğan ressam Paul Cézanne'ın izinden yürüyün, Musée Granet'de sanat eserlerini inceleyin ve pazarda alışveriş yapın.\n\n*   **Saignon (4 saat):** Luberon'daki şık tepelerdeki köyler her zaman büyüleyici. Ana şehir Apt'ın üzerindeki bir tepenin tepesinde yer alan küçük Saignon, Provence köylerinin en güzellerinden biri. Dar sokaklarında dolaşın, kireçtaşı evleri, şatosu ve yerel üreticilerden ürünler satan bakkalı ziyaret edin. Ardından, unutulmaz öğle yemeği mekanlarından birinde yerinizi ayırtın.\n\n*   **Gorges du Verdon (1 gün):** Provence'ın en muhteşem kanyonu olan Gorges du Verdon'da kartallara, akbabalara ve yaban domuzlarına ev sahipliği yapıyor. Moustiers Ste-Marie'den yavaşça araba sürerek kanyonun panoramik manzarasının tadını çıkarın. Bazı yerlerde, derin vadinin duvarları Eyfel Kulesi'nin iki katı yüksekliğe ulaşıyor.\n\n### 4. Breton İstiridyeleri ve Norman Peynirlerinin Tadını Çıkarın: 7 Günlük Bir Rota\n\nBu epik yolculukta bol miktarda istiridye ve peynir yiyeceğinizi hesaba katarak kemerlerinizi gevşetin. Sakin plajlar ve mitolojik adalar, mükemmel bir deniz havası eşliğinde size eşlik edecek. Bretonya ve Normandiya'yı keşfederken unutulmaz bir lezzet yolculuğuna çıkacaksınız.\n\n*   **Carnac (3 saat):** Her şeyin başladığı yer olan Carnac'ın dikili taşlarında yolculuğunuza başlayın. Bu anıtlar MÖ 5. yüzyıla kadar uzanıyor ve dünyanın en yüksek yoğunluktaki menhirlerini oluşturuyor. Rehberli turlara katılarak megalitleri çevreleyen mitleri ve efsaneleri öğrenin. Daha sonra Carnac'ın ilkel enerjisini emmek için çevredeki ormanlarda yürüyüş yapabilirsiniz.\n\n*   **Belle Île (2 gün):** Quiberon'dan Belle Île'ye yelken açın. Bu büyüleyici Breton adası, isminin hakkını veriyor: vahşi sahil şeridi, kumlu plajlar, pastel renklerde boyanmış geleneksel balıkçı köyleri ve ana yerleşim yeri Le Palais'te eğlenceli yemek ve içki mekanları sizi bekliyor. Etrafı dolaşmak için bir moped kiralayın.\n\n*   **St-Malo (1 gün):** Büyüleyici liman kenti St-Malo, dramatik bir manzara sunuyor. Dünyanın en büyük gelgit aralıklarından birine sahip olan bu güzel surlarla çevrili şehirde, fırtınalar sırasında yükselen dalgalar surları dövüyor. 17. yüzyılda korsanlar burada hüküm sürdü ve hayaletleri eski şehrin Arnavut kaldırımlı sokaklarında ve zengin özel konaklarında yaşamaya devam ediyor.\n\n*   **Mont St-Michel (Yarım gün):** Normandiya'ya daha dramatik bir giriş olamazdı. Kelt mitolojisi, Mont St-Michel'in ölülerin ruhlarının gönderildiği bir deniz mezarı olduğunu iddia ediyor. Tarihini derinden hissederek yaklaşın. Gün batımında manzarayı izlemek için geç kalın. Yerel olarak toplanan ürünlerle yemek yiyin ve Michelin \"yeşil yıldız\" ödüllü Auberge Sauvage'da konaklayın.\n\n*   **Cabourg (1 gün):** Normandiya'nın sanatla dolu Côte Fleurie'sinde Proust gibi tatil yapın. Zengin komşuları Deauville ve Trouville-sur-Mer ilgi odağı olsa da, Cabourg ziyaretçileri Belle Époque'a götüren sürükleyici bir müze sunuyor. Günü Cap Cabourg'dan Plage Le Home Varaville'e uzanan gün batımı tahta kaldırımında yürüyüş yaparak sonlandırın.\n\n*   **Pays d’Auge (2 gün):** İç kesimlere doğru yolculuk, farklı bir Normandiya'nın kapılarını açıyor: elma bahçeleri, güzel ahşap köyler ve sütü kremalı Camembert'e dönüşen ineklerle dolu tarlalar. Pays d’Auge'da sessiz köy yollarında kaybolarak geçireceğiniz iki günde, bir çiftlik içki fabrikasında Calvados'un nasıl yapıldığını öğrenebilir, Camembert köyüne hac ziyaretinde bulunabilir ve her yerde mükemmel yemekler yiyebilirsiniz.\n\n### 5. Eurostar ile Calais'den Alpler'e: Bir Hafta Sonu Rotası\n\nİngiltere'den Fransız Alpleri'ne giden kayakçılar genellikle Manş Denizi'ni geçtikten sonra Calais'den bu rotayı takip ediyor. Bu rota normalde 8 saat civarında sürüyor ve genellikle Reims veya Troyes'da geceleme yapılıyor. Vaktiniz varsa, ayaklarınızı gazdan çekin ve kabinlerle çevrili plajların, Şampanya mahzenlerinin ve birinci sınıf üzüm bağlarının keyfini çıkarın.\n\n*   **Calais (3 saat):** Araba feribotundan veya tren shuttle'ından inip şehre girin. Şehrin Flaman Rönesansı belediye binasının önünde poz veren şehrin ünlü burjuvalarının Rodin'in ünlü heykeline bir selam verin. Kumlu plaja gidin ve Calais'nin fantastik, dev mekanik ejderhasının içindeki sahilde bir tura katılın. L’Antre du Dragon restoranında DJ setleri, barbeküler ve temalı gecelerin tadını çıkarın.\n\n*   **Côte d’Opale (2 saat):** Deniz ve gökyüzündeki gri ve mavilerin etkileşimiyle adlandırılan bu sahil şeridi, sanatsal bir başyapıt. Bay of Wissant'ın, Flaman kırsalının ve uzaktaki beyaz tebeşir kayalıklarının muhteşem manzarasını Cap Blanc Nez'den seyredin. Wissant'ta su kenarında, gelgitin çekilmesiyle genişleyen plajda ayaklarınızı denize sokun.\n\n*   **Aÿ (Yarım gün):** Fransa'nın en iyi Art Deco mimarisine, görkemli Gotik katedraline ve dünyaca ünlü köpüklü şarabına ev sahipliği yapan geleneksel geceleme durağı Reims'i, daha az bilinen Aÿ ile değiştirin. Birinci sınıf Şampanya evlerinin tadını daha yavaş bir tempoda çıkarın ve son teknoloji ürünü Şampanya müzesi Pressoria'yı kaçırmayın. Ardından, uygun fiyatlı bir öğle yemeği için boulangerie'den atıştırmalıklar alın.\n\n*   **Dijon (1 gün):** 2022'de açılan göz kamaştırıcı Cité International de la Gastronomie et du Vin, Burgundy Dükalığı'nın yakışıklı merkezi ve modern Burgundy'nin gastronomi merkezi olan Dijon'da oyalanmak için tek başına bir neden. La Cité'deki yemek temalı sergiler, yemek alanı ve yemek pişirme ve şarap okulu, bol miktarda eğlence ve tadım fırsatı sunuyor. Burgundy şarabını tatmak zorunlu (sürücüler için tükürmeye izin verilir).\n\n*   **Annecy (2 saat):** Alpler'de nereye gittiğinize bağlı olarak, artık çok uzakta değilsiniz (Chamonix'e bir saat sayın). Vintage dondurma salonu Glacier des Alpes'den kestane, génépi veya çam aromalı bir dondurma ile Alp havasına girin. Annecy'nin romantik, Venedik tarzı eski kentinde gömülü olan gölün muhteşem manzarasının tadını çıkarın.\n\n## Meta Açıklama Önerisi\n\nFransa'yı keşfetmek için 5 muhteşem rota! Paris'ten Alpler'e, Normandiya'dan Güney Fransa'ya unutulmaz bir seyahat deneyimi yaşayın. Detaylı rehberimizle tatilinizi planlayın!\n\n## Sonuç\n\nFransa, her zevke ve bütçeye uygun seyahat seçenekleri sunan, keşfedilmeyi bekleyen bir ülke. Bu blog yazısında sunulan 5 farklı rota, size ilham verecek ve Fransa'nın en iyilerini görmeniz için size rehberlik edecek. Hangi rotayı seçerseniz seçin, unutulmaz bir maceraya atılacağınızdan emin olabilirsiniz. Şimdi plan yapmaya başlayın ve Fransa'nın büyülü dünyasına adım atın!"},"media":[{"src":"https://lp-cms-production.imgix.net/2025-03/shutterstock1029106939.jpg?auto=format,compress&amp;q=72&amp;fit=crop&amp;ar=1:1&amp;w=450&amp;h=450","alt":"Enjoy the cafes of Paris. Catarina Belova/Shutterstock","figcaption":"<b>Left:</b> Typical view of the Parisian street with tables of brasserie (cafe) in Paris, France.  <b>Right:</b> Visit golden-hued Arles. Adrienne Pitts for Lonely Planet"},{"src":"https://lp-cms-production.imgix.net/2024-08/france-john-harper-GettyImages-521655660-rfe.jpeg?auto=format,compress&amp;q=72&amp;fit=crop","alt":"Tourists sit on the sandy Dune du Pilat on the Bassin d’Arcachon at sunset.","figcaption":"Ride a bike to Dune du Pilat on the Bassin d’Arcachon. John Harper/Getty Images"},{"src":"https://lp-cms-production.imgix.net/2025-03/shutterstock2458687693.jpg?auto=format,compress&amp;q=72&amp;fit=crop&amp;ar=4:3&amp;w=800&amp;h=600","alt":"Beach umbrellas and blue loungers Nice, France. ","figcaption":"<b>Left:</b> Enjoy the beach in Nice. Lisa Liidemann / Shutterstock <b>Right:</b> Row your way through Verdon Gorge. Shutterstock"},{"src":"https://lp-cms-production.imgix.net/2024-10/LPT0812025.jpg?auto=format,compress&amp;q=72&amp;fit=crop","alt":"Mont St-Michel at mouth of Couesnon River at low tide.","figcaption":"Mont St-Michel at mouth of Couesnon River at low tide. Justin Foulkes for Lonely Planet"},{"src":"https://lp-cms-production.imgix.net/2024-10/GettyImages-1417906348.jpg?auto=format,compress&amp;q=72&amp;fit=crop","alt":"A light dusting of snow covers buildings on the edge of a canal in France's Annecy.","figcaption":"The village of Annecy in France. Getty Images"}],"id":1742847699304,"cities":["Paris","Blois","Vézère Vadisi","Carcassonne","Pont du Gard","Arles","Marsilya","Nantes","La Rochelle","Bordeaux","Arcachon","Bayonne","Nice","Menton","St-Tropez","Bormes-les-Mimosas","Aix-en-Provence","Saignon","Gorges du Verdon","Carnac","Belle Île","St-Malo","Mont St-Michel","Cabourg","Calais","Aÿ","Dijon","Annecy"],"description":"Fransa seyahat rotaları mı arıyorsunuz? Paris'ten Normandiya'ya, Alpler'den Güney Fransa'ya en iyi 5 güzergahı keşfedin. Unutulmaz bir Fransa tatili için tıklayın!","excerpt":"Fransa, gezginlerin hayallerini süsleyen zengin tarihi ve kültürel mirasıyla dolu bir ülke. Bu blog yazısında, Fransa'nın en ikonik yerlerini keşfetmek, Atlantik kıyısında keyifli bir yolculuk yapmak veya Güney Fransa'nın güneşli atmosferini solumak için 5 farklı seyahat rotasını inceleyeceğiz. Fransa'yı keşfedin!","keywords":["Fransa seyahat rotaları","Fransa tatili","Paris gezisi","Normandiya turu","Güney Fransa","Fransa gezilecek yerler"]}