{"title":"Uçakta Üst Sınıf Keyfi: İlk Yükseltmenizi Mükemmelleştirmenin 9 Yolu","featuredImage":{"src":"https://lp-cms-production.imgix.net/2024-11/ADL-headshot-cropped.jpg?auto=format,compress&q=72&crop=faces&fit=crop&w=64&h=64","alt":"Ann Douglas Lott","caption":"Maximize your flight upgrade with these tips. Cathay Pacific"},"output":{"title":"İlk Uçuşunuzda Bir Üst Sınıfa Geçtiğinizde Keyfinizi Katlamanın 9 Yolu","content":"Uçak yolculuklarında ekonomi sınıfında uzun uçuşların üstesinden gelmek için kendime göre bir formül geliştirmiştim. En iyi seyahat yastığı [https://trtltravel.com/products/trtl-travel-pillow] her zaman yanımdadır. Uçuştan önce bir kadeh şarap içip, uykuya dalmama yardımcı olması için bir antihistaminik alırım. İpek uyku maskem ise en iyi arkadaşım. Bu şekilde yolculuğun üstesinden gelebileceğimi biliyorum.\n\nAncak yakın zamanda yaşadığım bir üst sınıf deneyiminden sonra, seyahat etmenin en büyük keyiflerinden birini ilk kez yaşadığınızda nasıl en üst düzeye çıkarabileceğinizi düşünmeye başladım. İnanın bana, bu sadece bir kadeh şampanya ve tamamen yatan bir koltuktan çok daha fazlası.\n\nİster bu an için puanlarınızı biriktirmiş olun [https://www.lonelyplanet.com/articles/how-to-get-started-travel-points-airline-miles] ister son dakika şans eseri bir yükseltme yakalamış olun, iş sınıfı deneyiminizden en iyi şekilde yararlanmanızı sağlamak için bilmeniz gereken her şey burada.\n\n## 1. Kişisel Eşyalarınızın İçeriğini Yeniden Düşünün\n\nYeterli zamanınız varsa, çantanızı veya sırt çantanızı gözden geçirmek ve kontrol edilmiş valizinizdeki eşyalarla bazı değişiklikler yapmak isteyebilirsiniz [https://www.lonelyplanet.com/articles/packing-guide]. Havayolunun hangi olanakları sağlayacağını tam olarak bilmenin bir yolu olmasa da, ön taraftaki ekip diş fırçaları, terlikler ve uyku maskeleri gibi ürünler sağlayabilir. Koltuğunuz tam yatağa dönüşüyorsa, pijama getirmek isteyebilirsiniz.\n\nYukarıda havada iyi bir gece uykusu bekleyebilirsiniz. Bunun tadını çıkarın.\n\n## 2. Erken Gelin\n\nHavayoluna ve sınıfa bağlı olarak, bir yükseltme lounge erişimini içerebilir [https://www.lonelyplanet.com/articles/best-credit-cards-airport-lounge] – tıpkı Cathay Pacific Airways'de yakın zamanda aldığım iş sınıfı yükseltmemde olduğu gibi. Bir havaalanı lounge'ına girmekle kutsandığımda, kredi kartı seçimlerimi yeniden düşünüyorum [https://www.lonelyplanet.com/articles/best-travel-credit-cards]. Lounge erişimi ile uçuştan önce ücretsiz yiyecek ve içeceklerle karnınızı doyurabilirsiniz – belki bir kadeh şarap veya yatmadan önce sıcak bir çay.\n\nBangkok'tan [https://www.lonelyplanet.com/articles/top-things-to-do-in-bangkok] ABD'ye [https://www.lonelyplanet.com/usa] dönerken, Cathay lounge'ında bir bardak gazlı kola ve tereyağlı bir kurabiye aldım. Hong Kong'daki [https://www.lonelyplanet.com/china/hong-kong] aktarmam sırasında Pier Lounge'da kendime bir cappuccino hazırladım ve sadece rahatladım, tamamen umursamazdım. Lounge hayatının tadını çıkarın.\n\n## 3. Erken ve Şık Bir Şekilde Uçağa Binin\n\nEkonomi sınıfında uçarken, uçağa binmek için mümkün olan son dakikaya kadar beklemeyi tercih ederim – çünkü neden sardalya gibi sıkışık bir şekilde ekstra zaman geçirmek isteyeyim ki? İş sınıfında uçmak tamamen farklı bir hikayeydi. Uçağa biniş başlar başlamaz, yerime eşlik edilmek üzere ayrı, çok daha kısa iş sınıfı sırasına doğru ilerledim. Oturduktan sonra, bana sıcak bir havlu, bir hoş geldin içeceği (şampanya, meyve suyu veya Cathay'in popüler kivi-hindistan cevizi içeceği gibi) ve zarif bir iş sınıfına özel menü verildi. Arkanıza yaslanın ve özel ilginin tadını çıkarın.\n\n## 4. Pencere Kenarı Koltuğu İçin Stres Yapmayın\n\nÜst sınıf koltuklar genellikle koridor koltuklarıdır – ve dürüst olmak gerekirse bunun hiçbir önemi yoktur. Herkesin yayılmak için kendi özel kabini vardır, yani ekonomide olduğu gibi pencere kenarını kapmanın marjinal bir alan avantajı yoktur. Ve eğer gece uçuşuysa, özellikle önemi yoktur. Manzara tamamen karanlıksa, pencere kenarının anlamı nedir?\n\n## 5. Avantajlarınızı İnceleyin\n\nErken uçağa bindikten sonra (yukarıya bakın), kendinize alanınızın küçük bir turunu vermek için zaman ayırın. Etrafa bakın: yan bölmede ne var? Cathay Pacific, diş fırçası, diş macunu, ağız gargarası, vücut kremi ve uyku maskesi içeren bir tuvalet çantası sağladı. Ayak dayanağımda terlikler ve rahat bir yorgan, koltuğumda ise bir yastık beni bekliyordu. Eğlence seçeneklerine de göz atın. Ücretsiz Wi-Fi'ye uygun olabilirsiniz.\n\n## 6. Kabin Memurlarını Tanıyın\n\nHavayolu endüstrisindeki insanlar, ne tür bir biniş kartına sahip olursanız olun, tanışacağınız en nazik, en çalışkan ve en sabırlı insanlardan bazılarıdır. Açık görünüyor, ancak size temin ederim: ekonomiye kıyasla iş sınıfında daha fazla ilgi göreceksiniz. O seçkin koltuğun parasını ödediğinizde, ihtiyaçlarınız – ve daha da önemlisi, istekleriniz – karşılanacaktır.\n\nKabin memurlarının adlarını öğrenin ve onlara teşekkür edin. Hizmetleri özellikle örnek teşkil ediyorsa, havayoluna bir not gönderin ve onlara bildirin. Çok işe yarıyor.\n\n## 7. Ziyafete Hazır Olun\n\nHavayolu yemeklerinin olayı nedir? 9100 metrede (30.000ft) gerçekten şüpheli bazı yemekler yedim. Ancak bu yükseltme bildirimini aldıktan sonra, daha önce duyduğunuz (veya tattığınız) her şeyi unutabilirsiniz – çünkü muhtemelen uçağın arkasındaki insanlarınkinden ayrı, daha yüksek bir menünüz olacaktır. Akşam yemeği için beni uyanık tutmayacak hafif bir şeyler canım çekiyordu, bu yüzden salata ve ekmekle birlikte gelen mercimek çorbası sipariş ettim. Kahvaltı için açai yoğurtlu kase, sıcak hamur işleri ve taze meyveleri tercih ettim.\n\n## 8. İyi Bir Uyku Çekmeye Hazır Olun\n\nNeden Hong Kong'a 16 saatlik uçuşumda yedi saat uyuduğuma güvenebileceğinizi açıklayayım: Hayatım boyunca bahsettiğim bir şey olan hareket halindeki herhangi bir araçta neredeyse hiç uyuyamam. Bunun nedeni, hareket halindeyken neredeyse hiç tam yatay ve rahat olmamam. Yine de, bu uçuşta, tam yatan koltuğum (artı biraz melatonin), kolayca dinleneceğimi garanti etti.\n\nEn iyi sonuçlar için evdeki uyku rutininizi tekrarlamaya çalışın. Ekran süresini sınırlamayı ve uykuya dalmadan önce bir süre okumayı seviyorum.\n\n## 9. Bir veya İki İçecek Alın... veya Almayın\n\nBu, sık uçan yolcular topluluğu arasında tartışmalı bir konu olabilir ve bundan başka kesin bir cevabım yok: Sizin için ne işe yarıyorsa onu yapın. Uykuya dalmanıza, sinirlerinizi yatıştırmanıza veya deneyimi kutlamanıza yardımcı olması için bir içki almak istiyorsanız, bu tamamen sorun değil. Sadece yüksek rakımlarda içki içmenin kalp atış hızınızı artırdığını ve oksijen seviyenizi düşürdüğünü unutmayın, bu nedenle sizi riske atabilecek önceden var olan herhangi bir sağlık durumunuz varsa, bunun yerine bir fincan sıcak çayı tercih edebilirsiniz.\n\n**Meta Açıklama:** İlk uçuş yükseltmenizden en iyi şekilde yararlanın! Lounge erişimi, koltuk seçimi, yemekler ve daha fazlası hakkında ipuçları ile lüksün tadını çıkarın. Hemen okuyun!"},"media":[{"src":"https://lp-cms-production.imgix.net/2025-02/Cathay-Pacific-The-Pier-Lounge-in-Hong-Kong.jpeg?auto=format,compress&amp;q=72&amp;fit=crop","alt":"The Pier First Class Lounge in Hong Kong","figcaption":"The Pier First Class Lounge in Hong Kong. Cathay Pacific"},{"src":"https://lp-cms-production.imgix.net/2025-02/Cathay-Pacific-screen.jpg?auto=format,compress&amp;q=72&amp;fit=crop","alt":"business class seat view","figcaption":"My business-class seat. Ann Douglas Lott/Lonely Planet"},{"src":"https://lp-cms-production.imgix.net/2025-02/Cathay-Pacific-business-class-seat.jpeg?auto=format,compress&amp;q=72&amp;fit=crop","alt":"business class seat features","figcaption":"Taking inventory of my seat’s perks. Ann Douglas Lott/Lonely Planet"},{"src":"https://lp-cms-production.imgix.net/2025-02/Cathay-Pacific-breakfast.jpg?auto=format,compress&amp;q=72&amp;fit=crop","alt":"an acai bowl, pastries, fruit, and coffee","figcaption":"Breakfast is served. Ann Douglas Lott/Lonely Planet"},{"src":"https://lp-cms-production.imgix.net/2025-02/Cathay-Pacific-welcome-drink.jpg?auto=format,compress&amp;q=72&amp;fit=crop","alt":"having a drink on the plane","figcaption":"Cheers to business class! Ann Douglas Lott/Lonely Planet"}],"id":1742937366655,"cities":["Bangkok","Hong Kong"],"description":"İlk uçuşunuzda üst sınıfa mı yükseltildiniz? Lounge erişimi, konfor ve lezzetli yemeklerle bu deneyimi en üst düzeye çıkarmanın 9 yolunu keşfedin!","excerpt":"Uçak yolculuğunda üst sınıf deneyimi, sadece şampanya ve yatan koltuktan çok daha fazlasını sunar. İlk yükseltmenizde kişisel eşyalarınızdan lounge keyfine, ikramlardan uyku düzenine kadar her detayı planlayarak lüksün tadını çıkarın. İşte size bu deneyimi mükemmelleştirmenin 9 yolu!","keywords":["üst sınıf uçuş","uçak yolculuğu","business class","first class","uçuş yükseltmesi","lounge erişimi","havayolu yemekleri","konforlu uçuş"]}